{
  "users": {
    "62895403222792@s.whatsapp.net": {
      "afkTime": -1,
      "afkReason": "",
      "limit": 50,
      "level": 0,
      "autolevelup": true,
      "banned": false,
      "prem": false
    },
    "6285717062467@s.whatsapp.net": {
      "afkTime": -1,
      "afkReason": "",
      "limit": "Infinity",
      "level": 10,
      "autolevelup": true,
      "banned": false,
      "prem": false
    },
    "120363307758523980@newsletter": {
      "afkTime": -1,
      "afkReason": "",
      "limit": 50,
      "level": 0,
      "autolevelup": true
    },
    "6287727682210@s.whatsapp.net": {
      "afkTime": -1,
      "afkReason": "",
      "limit": "Infinity",
      "level": 0,
      "autolevelup": true,
      "banned": false,
      "prem": false
    },
    "6281255954942@s.whatsapp.net": {
      "afkTime": -1,
      "afkReason": "",
      "limit": 50,
      "level": 0,
      "autolevelup": true,
      "banned": false,
      "prem": false
    },
    "639302094684@s.whatsapp.net": {
      "afkTime": -1,
      "afkReason": "",
      "limit": 50,
      "level": 0,
      "autolevelup": true,
      "banned": false,
      "prem": false
    },
    "6285769668470@s.whatsapp.net": {
      "afkTime": -1,
      "afkReason": "",
      "limit": 50,
      "level": 0,
      "autolevelup": true,
      "banned": false,
      "prem": false
    },
    "6288902893105@s.whatsapp.net": {
      "afkTime": -1,
      "afkReason": "",
      "limit": 50,
      "level": 0,
      "autolevelup": true,
      "banned": false,
      "prem": false
    },
    "6287774569531@s.whatsapp.net": {
      "afkTime": -1,
      "afkReason": "",
      "limit": 50,
      "level": 0,
      "autolevelup": true,
      "banned": false,
      "prem": false
    },
    "6289603732786@s.whatsapp.net": {
      "afkTime": -1,
      "afkReason": "",
      "limit": 50,
      "level": 0,
      "autolevelup": true,
      "banned": false,
      "prem": false
    },
    "6285950723074@s.whatsapp.net": {
      "afkTime": -1,
      "afkReason": "",
      "limit": 50,
      "level": 0,
      "autolevelup": true,
      "banned": false,
      "prem": false
    },
    "120363365412644768@newsletter": {
      "afkTime": -1,
      "afkReason": "",
      "limit": 50,
      "level": 0,
      "autolevelup": true,
      "banned": false,
      "prem": false
    },
    "6285220188676@s.whatsapp.net": {
      "afkTime": -1,
      "afkReason": "",
      "limit": "Infinity",
      "level": 0,
      "autolevelup": true,
      "banned": false,
      "prem": false
    },
    "6285797442902@s.whatsapp.net": {
      "afkTime": -1,
      "afkReason": "",
      "limit": 50,
      "level": 0,
      "autolevelup": true,
      "banned": false,
      "prem": false
    },
    "120363323868732166@newsletter": {
      "afkTime": -1,
      "afkReason": "",
      "limit": 50,
      "level": 0,
      "autolevelup": true,
      "banned": false,
      "prem": false
    },
    "120363280576631666@newsletter": {
      "afkTime": -1,
      "afkReason": "",
      "limit": 50,
      "level": 0,
      "autolevelup": true,
      "banned": false,
      "prem": false
    },
    "120363330381973108@newsletter": {
      "afkTime": -1,
      "afkReason": "",
      "limit": 50,
      "level": 0,
      "autolevelup": true,
      "banned": false,
      "prem": false
    }
  },
  "chats": {
    "6285717062467@s.whatsapp.net": {
      "cai": false,
      "selfgc": false,
      "mute": false,
      "wlcm": true,
      "nsfw": false,
      "antitoxic": false,
      "antilink": false,
      "antilinkyt": false,
      "antilinktt": false,
      "antivirtex": true,
      "antipanel": false,
      "antilinkv2": false,
      "autodown": false,
      "notification": {
        "status": false,
        "text_left": "",
        "text_welcome": ""
      }
    },
    "120363307758523980@newsletter": {
      "cai": false,
      "selfgc": false,
      "mute": false,
      "wlcm": true,
      "nsfw": false,
      "antitoxic": false,
      "antilink": false,
      "antilinkyt": false,
      "antilinktt": false,
      "antivirtex": true,
      "antipanel": false,
      "antilinkv2": false,
      "autodown": false,
      "notification": {
        "status": false,
        "text_left": "",
        "text_welcome": ""
      }
    },
    "6287727682210@s.whatsapp.net": {
      "cai": false,
      "selfgc": false,
      "mute": false,
      "wlcm": true,
      "nsfw": false,
      "antitoxic": false,
      "antilink": false,
      "antilinkyt": false,
      "antilinktt": false,
      "antivirtex": true,
      "antipanel": false,
      "antilinkv2": false,
      "autodown": false,
      "notification": {
        "status": false,
        "text_left": "",
        "text_welcome": ""
      }
    },
    "62895403222792@s.whatsapp.net": {
      "cai": false,
      "selfgc": false,
      "mute": false,
      "wlcm": true,
      "nsfw": false,
      "antitoxic": false,
      "antilink": false,
      "antilinkyt": false,
      "antilinktt": false,
      "antivirtex": true,
      "antipanel": false,
      "antilinkv2": false,
      "autodown": false,
      "notification": {
        "status": false,
        "text_left": "",
        "text_welcome": ""
      }
    },
    "120363386611878298@g.us": {
      "cai": false,
      "selfgc": false,
      "mute": false,
      "wlcm": true,
      "nsfw": false,
      "antitoxic": false,
      "antilink": false,
      "antilinkyt": false,
      "antilinktt": false,
      "antivirtex": true,
      "antipanel": false,
      "antilinkv2": false,
      "autodown": false,
      "notification": {
        "status": false,
        "text_left": "",
        "text_welcome": ""
      }
    },
    "120363347021473313@g.us": {
      "cai": false,
      "selfgc": false,
      "mute": false,
      "wlcm": true,
      "nsfw": false,
      "antitoxic": false,
      "antilink": false,
      "antilinkyt": false,
      "antilinktt": false,
      "antivirtex": true,
      "antipanel": false,
      "antilinkv2": false,
      "autodown": false,
      "notification": {
        "status": false,
        "text_left": "",
        "text_welcome": ""
      }
    },
    "120363365412644768@newsletter": {
      "cai": false,
      "selfgc": false,
      "mute": false,
      "wlcm": true,
      "nsfw": false,
      "antitoxic": false,
      "antilink": false,
      "antilinkyt": false,
      "antilinktt": false,
      "antivirtex": true,
      "antipanel": false,
      "antilinkv2": false,
      "autodown": false,
      "notification": {
        "status": false,
        "text_left": "",
        "text_welcome": ""
      }
    },
    "6285220188676@s.whatsapp.net": {
      "cai": false,
      "selfgc": false,
      "mute": false,
      "wlcm": true,
      "nsfw": false,
      "antitoxic": false,
      "antilink": false,
      "antilinkyt": false,
      "antilinktt": false,
      "antivirtex": true,
      "antipanel": false,
      "antilinkv2": false,
      "autodown": false,
      "notification": {
        "status": false,
        "text_left": "",
        "text_welcome": ""
      }
    },
    "6285797442902@s.whatsapp.net": {
      "cai": false,
      "selfgc": false,
      "mute": false,
      "wlcm": true,
      "nsfw": false,
      "antitoxic": false,
      "antilink": false,
      "antilinkyt": false,
      "antilinktt": false,
      "antivirtex": true,
      "antipanel": false,
      "antilinkv2": false,
      "autodown": false,
      "notification": {
        "status": false,
        "text_left": "",
        "text_welcome": ""
      }
    },
    "120363323868732166@newsletter": {
      "cai": false,
      "selfgc": false,
      "mute": false,
      "wlcm": true,
      "nsfw": false,
      "antitoxic": false,
      "antilink": false,
      "antilinkyt": false,
      "antilinktt": false,
      "antivirtex": true,
      "antipanel": false,
      "antilinkv2": false,
      "autodown": false,
      "notification": {
        "status": false,
        "text_left": "",
        "text_welcome": ""
      }
    },
    "120363280576631666@newsletter": {
      "cai": false,
      "selfgc": false,
      "mute": false,
      "wlcm": true,
      "nsfw": false,
      "antitoxic": false,
      "antilink": false,
      "antilinkyt": false,
      "antilinktt": false,
      "antivirtex": true,
      "antipanel": false,
      "antilinkv2": false,
      "autodown": false,
      "notification": {
        "status": false,
        "text_left": "",
        "text_welcome": ""
      }
    },
    "120363330381973108@newsletter": {
      "cai": false,
      "selfgc": false,
      "mute": false,
      "wlcm": true,
      "nsfw": false,
      "antitoxic": false,
      "antilink": false,
      "antilinkyt": false,
      "antilinktt": false,
      "antivirtex": true,
      "antipanel": false,
      "antilinkv2": false,
      "autodown": false,
      "notification": {
        "status": false,
        "text_left": "",
        "text_welcome": ""
      }
    }
  },
  "game": {},
  "database": {},
  "settings": {
    "62895403222792@s.whatsapp.net": {
      "status": 0,
      "autobio": false,
      "autoread": false
    },
    "6287727682210@s.whatsapp.net": {
      "status": 0,
      "autobio": false,
      "autoread": false
    },
    "6285220188676": {
      "status": 0,
      "autobio": false,
      "autoread": false
    },
    "6287727682210": {
      "status": 0,
      "autobio": false,
      "autoread": false
    }
  },
  "anonymous": {},
  "setting": {},
  "others": {},
  "sticker": {},
  "botNumber": "6285220188676"
}